python3_anticaptcha/__init__.py
python3_anticaptcha/__version__.py
python3_anticaptcha/amazon_waf.py
python3_anticaptcha/config.py
python3_anticaptcha/control.py
python3_anticaptcha/custom_task.py
python3_anticaptcha/friendly_captcha.py
python3_anticaptcha/fun_captcha.py
python3_anticaptcha/gee_test.py
python3_anticaptcha/image_to_coordinates.py
python3_anticaptcha/image_to_text.py
python3_anticaptcha/prosopo_captcha.py
python3_anticaptcha/recaptcha_v2.py
python3_anticaptcha/recaptcha_v3.py
python3_anticaptcha/turnstile.py
python3_anticaptcha/core/__init__.py
python3_anticaptcha/core/aio_captcha_instrument.py
python3_anticaptcha/core/base.py
python3_anticaptcha/core/captcha_instrument.py
python3_anticaptcha/core/const.py
python3_anticaptcha/core/context_instr.py
python3_anticaptcha/core/enum.py
python3_anticaptcha/core/serializer.py
python3_anticaptcha/core/sio_captcha_instrument.py
python3_anticaptcha/core/utils.py
python3_anticaptcha-2.2.1.dist-info/licenses/LICENSE
python3_anticaptcha-2.2.1.dist-info/METADATA
python3_anticaptcha-2.2.1.dist-info/WHEEL
python3_anticaptcha-2.2.1.dist-info/top_level.txt
python3_anticaptcha-2.2.1.dist-info/RECORD
