Metadata-Version: 2.4
Name: python3-anticaptcha
Version: 2.2.1
Summary: Python 3.9+ RuCaptcha library with AIO module.
Author-email: AndreiDrang <python-captcha@pm.me>
License-Expression: MIT
Project-URL: Homepage, https://andreidrang.github.io/python3-anticaptcha
Project-URL: Documentation, https://andreidrang.github.io/python3-anticaptcha
Project-URL: Repository, https://github.com/AndreiDrang/python3-anticaptcha
Project-URL: Issues, https://github.com/AndreiDrang/python3-anticaptcha/issues
Project-URL: Changelog, https://github.com/AndreiDrang/python3-anticaptcha/releases
Keywords: captcha,anticaptcha,deathbycaptcha,recaptcha,geetest,hcaptcha,capypuzzle,rotatecaptcha,funcaptcha,keycaptcha,python3,recaptcha,captcha,security,tencent,atb_captcha,python-library,python-anticaptcha,anticaptcha-client,yandex,turnstile,amazon,amazon_waf,friendly-captcha
Classifier: Development Status :: 5 - Production/Stable
Classifier: Programming Language :: Python
Classifier: Programming Language :: Python :: 3
Classifier: Programming Language :: Python :: 3 :: Only
Classifier: Programming Language :: Python :: 3.9
Classifier: Programming Language :: Python :: 3.10
Classifier: Programming Language :: Python :: 3.11
Classifier: Programming Language :: Python :: 3.12
Classifier: Framework :: AsyncIO
Classifier: Operating System :: Unix
Classifier: Operating System :: Microsoft :: Windows
Classifier: Operating System :: MacOS
Requires-Python: >=3.9
License-File: LICENSE
Requires-Dist: requests>=2.21.0
Requires-Dist: aiohttp>=3.9.2
Requires-Dist: msgspec<0.20,>=0.18
Requires-Dist: tenacity<10,>=8
Dynamic: license-file
